.gitignore
CONTRIBUTING.md
LICENSE
MANIFEST.in
Makefile
README.md
precommit.sh
requirements.txt
sample_text.html
setup.py
.github/dependabot.yml
.github/workflows/ci.yml
notofonttools.egg-info/PKG-INFO
notofonttools.egg-info/SOURCES.txt
notofonttools.egg-info/dependency_links.txt
notofonttools.egg-info/entry_points.txt
notofonttools.egg-info/requires.txt
notofonttools.egg-info/top_level.txt
nototools/__init__.py
nototools/_version.py
nototools/add_vs_cmap.py
nototools/android_patches.py
nototools/autofix_for_phase3.py
nototools/autofix_for_release.py
nototools/charsets.py
nototools/check_familyname_and_styles.py
nototools/cldr_data.py
nototools/cmap_block_coverage.py
nototools/cmap_data.py
nototools/codepoint_groups.txt
nototools/collect_cldr_punct.py
nototools/compare_cmap_data.py
nototools/compare_fonts.py
nototools/compare_summary.py
nototools/coverage.py
nototools/create_image.py
nototools/decompose_ttc.py
nototools/drop_hints.py
nototools/dump_otl.py
nototools/extra_locale_data.py
nototools/fix_khmer_and_lao_coverage.py
nototools/fix_noto_cjk_thin.py
nototools/font_caching.py
nototools/font_data.py
nototools/gen_cplist.py
nototools/generate_dingbats_html.py
nototools/generate_fontdiff_input.py
nototools/generate_lang_font_table.py
nototools/generate_sample_from_exemplar.py
nototools/generate_sample_text.py
nototools/generate_sample_text_html.py
nototools/generate_sample_texts.sh
nototools/generate_samples.py
nototools/generate_waterfall_html.py
nototools/glyph_area_pen.py
nototools/gpos_diff.py
nototools/gsub_diff.py
nototools/hb_input.py
nototools/lang_data.py
nototools/lint_cmap_reqs.py
nototools/lint_config.py
nototools/match_font_names.py
nototools/merge_fonts.py
nototools/merge_noto.py
nototools/mti_cmap_data.py
nototools/noto_cmap_reqs.py
nototools/noto_data.py
nototools/noto_font_cmaps.py
nototools/noto_font_coverage.py
nototools/noto_fonts.py
nototools/noto_lint.py
nototools/noto_names.py
nototools/notoconfig.py
nototools/notodiff.py
nototools/opentype_data.py
nototools/py23.py
nototools/render.py
nototools/sample_text.html
nototools/sample_with_font.py
nototools/scale.py
nototools/shape_diff.py
nototools/subset.py
nototools/subset_font_cmap.py
nototools/subset_symbols.py
