Metadata-Version: 2.4
Name: notofonttools
Version: 0.3.2
Summary: Noto font tools
Home-page: https://github.com/googlefonts/nototools
Author: Noto Authors
Author-email: noto-font@googlegroups.com
License: Apache
Requires-Python: >=3.7
License-File: LICENSE
Requires-Dist: fontTools
Provides-Extra: shapediff
Requires-Dist: booleanOperations; extra == "shapediff"
Requires-Dist: defcon; extra == "shapediff"
Requires-Dist: Pillow; extra == "shapediff"
Dynamic: author
Dynamic: author-email
Dynamic: description
Dynamic: home-page
Dynamic: license
Dynamic: license-file
Dynamic: provides-extra
Dynamic: requires-dist
Dynamic: requires-python
Dynamic: summary
